cprotobuf/__init__.py
cprotobuf/internal.so
cprotobuf/plugin_pb.py
cprotobuf_lc-0.1.5.data/scripts/protoc-gen-cprotobuf
cprotobuf_lc-0.1.5.dist-info/DESCRIPTION.rst
cprotobuf_lc-0.1.5.dist-info/METADATA
cprotobuf_lc-0.1.5.dist-info/RECORD
cprotobuf_lc-0.1.5.dist-info/WHEEL
cprotobuf_lc-0.1.5.dist-info/metadata.json
cprotobuf_lc-0.1.5.dist-info/top_level.txt
