Metadata-Version: 2.0
Name: cprotobuf-lc
Version: 0.1.5
Summary: cprotobuf maintained by LeanCloud
Home-page: https://github.com/leancloud/cprotobuf
Author: huangyi
Author-email: yi.codeplayer@gmail.com
License: UNKNOWN
Platform: UNKNOWN
